.installed.cfg
CHANGES.txt
INSTALL.txt
LICENSE.txt
MANIFEST.in
README.txt
TODO.txt
app.cfg
app.cfg.in
base.cfg
bootstrap.py
buildout.cfg
configure.py
i18n.cfg
setup.py
testing.cfg
versions.cfg
src/mypypi/__init__.py
src/mypypi/api.py
src/mypypi/authentication.py
src/mypypi/authentication.zcml
src/mypypi/bootstrap.py
src/mypypi/bootstrap.zcml
src/mypypi/breadcrumb.py
src/mypypi/breadcrumb.zcml
src/mypypi/classifiers.data
src/mypypi/configure.zcml
src/mypypi/exceptions.py
src/mypypi/i18n.py
src/mypypi/interfaces.py
src/mypypi/layer.py
src/mypypi/layer.zcml
src/mypypi/logger.py
src/mypypi/logger.zcml
src/mypypi/package.py
src/mypypi/package.zcml
src/mypypi/project.py
src/mypypi/project.zcml
src/mypypi/public.py
src/mypypi/public.zcml
src/mypypi/release.py
src/mypypi/release.zcml
src/mypypi/site.py
src/mypypi/site.zcml
src/mypypi/storage.py
src/mypypi/storage.zcml
src/mypypi/versionpredicate.py
src/mypypi/wsgi.py
src/mypypi.egg-info/PKG-INFO
src/mypypi.egg-info/SOURCES.txt
src/mypypi.egg-info/dependency_links.txt
src/mypypi.egg-info/entry_points.txt
src/mypypi.egg-info/namespace_packages.txt
src/mypypi.egg-info/not-zip-safe
src/mypypi.egg-info/requires.txt
src/mypypi.egg-info/top_level.txt
src/mypypi/admin/README.txt
src/mypypi/admin/__init__.py
src/mypypi/admin/configure.zcml
src/mypypi/admin/export.py
src/mypypi/admin/export.zcml
src/mypypi/admin/fsstorage.pt
src/mypypi/admin/fsstorage.py
src/mypypi/admin/fsstorage.zcml
src/mypypi/admin/group.py
src/mypypi/admin/group.zcml
src/mypypi/admin/groups.pt
src/mypypi/admin/package.py
src/mypypi/admin/package.zcml
src/mypypi/admin/package_releases.pt
src/mypypi/admin/project.py
src/mypypi/admin/project.zcml
src/mypypi/admin/projects.pt
src/mypypi/admin/public.py
src/mypypi/admin/public.zcml
src/mypypi/admin/public_files.pt
src/mypypi/admin/publics.pt
src/mypypi/admin/release.py
src/mypypi/admin/release.zcml
src/mypypi/admin/release_files.pt
src/mypypi/admin/role.py
src/mypypi/admin/role.zcml
src/mypypi/admin/roles_package.pt
src/mypypi/admin/roles_site.pt
src/mypypi/admin/site.py
src/mypypi/admin/site.zcml
src/mypypi/admin/site_history.pt
src/mypypi/admin/site_packages.pt
src/mypypi/admin/site_test.pt
src/mypypi/admin/user.py
src/mypypi/admin/user.zcml
src/mypypi/admin/users.pt
