Metadata-Version: 2.1
Name: mypypi
Version: 2.0.3
Summary: My Python Package Index (Standalone Server)
Home-page: https://pypi.org/pypi/mypypi
Author: Projekt01 GmbH, 6330 Cham, Switzerland
Author-email: dev@projekt01.ch
License: ZPL 2.1
Keywords: python buildout package index server egg pypi mirror private
Platform: UNKNOWN
Classifier: Development Status :: 4 - Beta
Classifier: Environment :: Web Environment
Classifier: Intended Audience :: Developers
Classifier: License :: OSI Approved :: Zope Public License
Classifier: Programming Language :: Python
Classifier: Natural Language :: English
Classifier: Operating System :: OS Independent
Classifier: Topic :: Internet :: WWW/HTTP
Classifier: Framework :: Zope3
Provides-Extra: test
